spider/__init__.py
spider/base/__init__.py
spider/base/easy_chain.py
spider/base/easy_item.py
spider/base/easy_item_backends.py
spider/base/easy_obj.py
spider/components/__init__.py
spider/components/base.py
spider/components/downloader.py
spider/components/parser.py
spider/components/pipeline.py
spider/network/__init__.py
spider/network/request.py
spider/network/response.py
spider/utils/__init__.py
spider/utils/exceptions.py
spider/utils/loader.py
spider/utils/trackref.py
celery_spider-0.1.1.dist-info/METADATA
celery_spider-0.1.1.dist-info/WHEEL
celery_spider-0.1.1.dist-info/RECORD
